{"name":"Bezier Maker",
"description":"A short javascript experiment i did, because i watched a video about bézier-curves.<br><br> You can change the degree in the source code, as i was too lazy to add any UI or settings on the website itself.<br>Should be in the setup() function. First four are position related and last one is degree.<br><br>You can move around nodes by just drag clicking them.",
"date":null,
"state":"finished",
"tech":[
    "javascript","html","css"
],
"imgs":[
    "/imgs/projects/bezier.png",
    "/imgs/projects/bezier2.png",
    "https://cdn.discordapp.com/attachments/872625271310794763/914533322414252113/GIF_28.11.2021_15-45-36.gif"
],"links":[
    {
        "name":"Github",
        "url":"https://github.com/jannik323/beziermaker"
    },{
        "name":"Website",
        "url":"https://jannik323.github.io/beziermaker/"
    }
]}